json_manager/__init__.py
json_manager/json_attributdict.py
json_manager/json_setup.py
json_manager2.0-1.1.0.dist-info/LICENSE
json_manager2.0-1.1.0.dist-info/METADATA
json_manager2.0-1.1.0.dist-info/WHEEL
json_manager2.0-1.1.0.dist-info/top_level.txt
json_manager2.0-1.1.0.dist-info/RECORD
