Metadata-Version: 2.2
Name: json-manager2.0
Version: 1.1.0
Summary: An json manager
Home-page: https://github.com/BOXERRMD/JsonManager
Author: BOXERRMD
Author-email: vagabonwalybi@gmail.com
Project-URL: Documentation, https://github.com/BOXERRMD/JsonManager/wiki
Project-URL: GitHub, https://github.com/BOXERRMD/JsonManager
Classifier: Programming Language :: Python :: 3
Classifier: License :: OSI Approved :: MIT License
Classifier: Natural Language :: English
Classifier: Operating System :: Microsoft :: Windows :: Windows 11
Classifier: Operating System :: Microsoft :: Windows :: Windows 10
Requires-Python: >=3.9
License-File: LICENSE
Dynamic: author
Dynamic: author-email
Dynamic: classifier
Dynamic: description
Dynamic: description-content-type
Dynamic: home-page
Dynamic: project-url
Dynamic: requires-python
Dynamic: summary
